superdocs/__init__.py
superdocs/_version.py
superdocs/cli.py
superdocs/langgraph.py
superdocs/link_extractor.py
superdocs/main.py
superdocs/splash.py
superdocs-0.2.1.dist-info/METADATA
superdocs-0.2.1.dist-info/WHEEL
superdocs-0.2.1.dist-info/entry_points.txt
superdocs-0.2.1.dist-info/licenses/LICENSE
superdocs-0.2.1.dist-info/RECORD
