Metadata-Version: 2.4
Name: superdocs
Version: 0.2.1
Summary: Enhanced MCP server for documentation with superpowers
License-Expression: MIT
License-File: LICENSE
Requires-Python: >=3.10
Requires-Dist: httpx>=0.28.1
Requires-Dist: markdownify>=1.1.0
Requires-Dist: mcp[cli]>=1.4.1
Requires-Dist: pyyaml>=6.0.1
Provides-Extra: test
Requires-Dist: pytest-asyncio>=0.25.3; extra == 'test'
Requires-Dist: pytest-cov>=6.0.0; extra == 'test'
Requires-Dist: pytest-mock>=3.14.0; extra == 'test'
Requires-Dist: pytest-socket>=0.7.0; extra == 'test'
Requires-Dist: pytest-timeout>=2.3.1; extra == 'test'
Requires-Dist: pytest>=8.3.4; extra == 'test'
Requires-Dist: ruff>=0.9.7; extra == 'test'
